trainer.py
common/__init__.py
common/dataset.py
common/fairscale.py
common/logging.py
common/storage.py
common/utils.py
models/__init__.py
models/pixart/__init__.py
models/pixart/diffusion.py
models/pixart/dit.py
models/sgm/__init__.py
models/sgm/attention.py
models/sgm/autoencoder.py
models/sgm/encoder_util.py
models/sgm/encoders.py
models/sgm/model.py
models/sgm/model_util.py
models/sgm/vae_model.py
modules/__init__.py
modules/sd_model_diffusers.py
modules/sdxl_dpo_hfdataset.py
modules/sdxl_model.py
modules/sdxl_model_diffusers.py
modules/sdxl_utils.py
modules/train.py
modules/train_diffusers.py
modules/train_lcm.py
modules/train_lycoris.py
modules/train_pixart.py
modules/train_refiner.py
modules/train_sd_diffusers.py
naifu-0.1.3.dist-info/LICENSE
naifu-0.1.3.dist-info/METADATA
naifu-0.1.3.dist-info/WHEEL
naifu-0.1.3.dist-info/entry_points.txt
naifu-0.1.3.dist-info/top_level.txt
naifu-0.1.3.dist-info/RECORD
