Metadata-Version: 2.1
Name: naifu
Version: 0.1.3
Summary: naifu is designed for training generative models with various configurations and features.
Home-page: https://github.com/mikubill/naifu-diffusion
Author: Mikubill
Author-email: 31246794+Mikubill@users.noreply.github.com
License: MIT
License-File: LICENSE
Requires-Dist: numpy
Requires-Dist: accelerate
Requires-Dist: lightning >=2.0
Requires-Dist: omegaconf >=2.1.1
Requires-Dist: lightning-lite
Requires-Dist: transformers >=4.25.1
Requires-Dist: datasets >=2.17
Requires-Dist: diffusers >=0.18
Requires-Dist: bitsandbytes >=0.41
Requires-Dist: wandb
Requires-Dist: ftfy
Requires-Dist: torchvision
Requires-Dist: requests
Requires-Dist: timm
Requires-Dist: safetensors
Requires-Dist: tensorboard
Requires-Dist: h5py
Requires-Dist: open-clip-torch
Requires-Dist: einops
Requires-Dist: scipy
Requires-Dist: torch-ema
Requires-Dist: opencv-python
